tooey/__init__.py
tooey/__version__.py
tooey/tooey.py
tooey-0.4.0.dist-info/LICENSE
tooey-0.4.0.dist-info/METADATA
tooey-0.4.0.dist-info/WHEEL
tooey-0.4.0.dist-info/top_level.txt
tooey-0.4.0.dist-info/RECORD
