Metadata-Version: 2.1
Name: tooey
Version: 0.4.0
Summary: Automatically turn script arguments into an interactive terminal interface
Home-page: https://github.com/simonrob/tooey
Author: Simon Robinson
Author-email: simon@robinson.ac
License: Apache 2.0
Project-URL: Bug Tracker, https://github.com/simonrob/tooey/issues
Project-URL: Source Code, https://github.com/simonrob/tooey
Classifier: Development Status :: 4 - Beta
Classifier: Operating System :: OS Independent
Classifier: Environment :: Console
Classifier: Programming Language :: Python
Classifier: Programming Language :: Python :: 3
Classifier: Intended Audience :: Developers
Classifier: Topic :: Terminals
Classifier: Topic :: Desktop Environment
Classifier: Topic :: Software Development :: Build Tools
Classifier: License :: OSI Approved :: Apache Software License
License-File: LICENSE
